changelog/.gitempty
dkist_processing_dlnirsp/__init__.py
dkist_processing_dlnirsp/config.py
dkist_processing_dlnirsp/dev_scripts/__init__.py
dkist_processing_dlnirsp/dev_scripts/test_slitbeam_group_assignment.py
dkist_processing_dlnirsp/models/__init__.py
dkist_processing_dlnirsp/models/constants.py
dkist_processing_dlnirsp/models/fits_access.py
dkist_processing_dlnirsp/models/parameters.py
dkist_processing_dlnirsp/models/tags.py
dkist_processing_dlnirsp/models/task_name.py
dkist_processing_dlnirsp/parsers/__init__.py
dkist_processing_dlnirsp/parsers/dlnirsp_l0_fits_access.py
dkist_processing_dlnirsp/parsers/dlnirsp_l1_fits_acess.py
dkist_processing_dlnirsp/parsers/mosaic.py
dkist_processing_dlnirsp/parsers/task.py
dkist_processing_dlnirsp/parsers/time.py
dkist_processing_dlnirsp/parsers/wcs_corrections.py
dkist_processing_dlnirsp/tasks/__init__.py
dkist_processing_dlnirsp/tasks/bad_pixel_map.py
dkist_processing_dlnirsp/tasks/dark.py
dkist_processing_dlnirsp/tasks/dlnirsp_base.py
dkist_processing_dlnirsp/tasks/geometric.py
dkist_processing_dlnirsp/tasks/ifu_drift.py
dkist_processing_dlnirsp/tasks/instrument_polarization.py
dkist_processing_dlnirsp/tasks/l1_output_data.py
dkist_processing_dlnirsp/tasks/lamp.py
dkist_processing_dlnirsp/tasks/linearity_correction.py
dkist_processing_dlnirsp/tasks/movie.py
dkist_processing_dlnirsp/tasks/parse.py
dkist_processing_dlnirsp/tasks/quality_metrics.py
dkist_processing_dlnirsp/tasks/science.py
dkist_processing_dlnirsp/tasks/solar.py
dkist_processing_dlnirsp/tasks/wavelength_calibration.py
dkist_processing_dlnirsp/tasks/write_l1.py
dkist_processing_dlnirsp/tasks/mixin/__init__.py
dkist_processing_dlnirsp/tasks/mixin/corrections.py
dkist_processing_dlnirsp/tasks/mixin/group_id.py
dkist_processing_dlnirsp/tests/__init__.py
dkist_processing_dlnirsp/tests/conftest.py
dkist_processing_dlnirsp/tests/test_assemble_quality.py
dkist_processing_dlnirsp/tests/test_bad_pixel_map.py
dkist_processing_dlnirsp/tests/test_corrections.py
dkist_processing_dlnirsp-0.34.2.dist-info/METADATA
dkist_processing_dlnirsp-0.34.2.dist-info/WHEEL
dkist_processing_dlnirsp-0.34.2.dist-info/entry_points.txt
dkist_processing_dlnirsp-0.34.2.dist-info/top_level.txt
dkist_processing_dlnirsp-0.34.2.dist-info/RECORD
