Metadata-Version: 2.4
Name: dkist-processing-dlnirsp
Version: 0.34.2
Summary: Science processing code for the DLNIRSP instrument on DKIST
Author-email: NSO / AURA <dkistdc@nso.edu>
License: BSD-3-Clause
Project-URL: Homepage, https://nso.edu/dkist/data-center/
Project-URL: Repository, https://bitbucket.org/dkistdc/dkist-processing-dlnirsp/
Project-URL: Documentation, https://docs.dkist.nso.edu/projects/dl-nirsp
Project-URL: Help, https://nso.atlassian.net/servicedesk/customer/portal/5
Classifier: Programming Language :: Python
Classifier: Programming Language :: Python :: 3
Classifier: Programming Language :: Python :: 3.13
Requires-Python: >=3.13
Requires-Dist: dkist-processing-common==12.2.0
Requires-Dist: dkist-processing-math==2.2.1
Requires-Dist: dkist-processing-pac==3.1.1
Requires-Dist: dkist-header-validator==5.3.0
Requires-Dist: dkist-fits-specifications==4.20.0
Requires-Dist: dkist-spectral-lines==3.0.0
Requires-Dist: dkist-service-configuration==4.2.0
Requires-Dist: astropy==7.0.2
Requires-Dist: numpy==2.2.5
Requires-Dist: numba==0.61.2
Requires-Dist: scipy==1.15.3
Requires-Dist: peakutils==1.3.5
Requires-Dist: sunpy==6.1.1
Requires-Dist: reproject==0.19.0
Requires-Dist: imageio-ffmpeg==0.6.0
Requires-Dist: asdf==3.5.0
Requires-Dist: solar-wavelength-calibration==2.0.0
Provides-Extra: test
Requires-Dist: pytest; extra == "test"
Requires-Dist: pytest-cov; extra == "test"
Requires-Dist: pytest-xdist; extra == "test"
Requires-Dist: pytest-mock; extra == "test"
Requires-Dist: hypothesis; extra == "test"
Requires-Dist: towncrier; extra == "test"
Requires-Dist: dkist-data-simulator>=5.2.6; extra == "test"
Requires-Dist: pydantic; extra == "test"
Requires-Dist: dkist-processing-dlnirsp[inventory]; extra == "test"
Requires-Dist: dkist-processing-dlnirsp[asdf]; extra == "test"
Requires-Dist: dkist-processing-dlnirsp[quality]; extra == "test"
Provides-Extra: inventory
Requires-Dist: dkist-processing-common[inventory]; extra == "inventory"
Requires-Dist: dkist-inventory==1.11.2; extra == "inventory"
Provides-Extra: asdf
Requires-Dist: dkist-processing-common[asdf]; extra == "asdf"
Requires-Dist: dkist-inventory[asdf]==1.11.2; extra == "asdf"
Provides-Extra: quality
Requires-Dist: dkist-quality==2.0.0; extra == "quality"
Provides-Extra: grogu
Requires-Dist: dkist; extra == "grogu"
Requires-Dist: pyparsing; extra == "grogu"
Requires-Dist: dkist-processing-dlnirsp[test]; extra == "grogu"
Requires-Dist: dkist-processing-dlnirsp[quality]; extra == "grogu"
Requires-Dist: dkist-processing-dlnirsp[asdf]; extra == "grogu"
Provides-Extra: docs
Requires-Dist: sphinx; extra == "docs"
Requires-Dist: sphinx-astropy; extra == "docs"
Requires-Dist: sphinx-changelog; extra == "docs"
Requires-Dist: sphinx-autoapi; extra == "docs"
Requires-Dist: pytest; extra == "docs"
Requires-Dist: towncrier; extra == "docs"
Requires-Dist: dkist-sphinx-theme; extra == "docs"
Provides-Extra: frozen
Requires-Dist: Deprecated==1.3.1; extra == "frozen"
Requires-Dist: ImageIO==2.37.2; extra == "frozen"
Requires-Dist: Jinja2==3.1.6; extra == "frozen"
Requires-Dist: Mako==1.3.10; extra == "frozen"
Requires-Dist: MarkupSafe==3.0.3; extra == "frozen"
Requires-Dist: PIMS==0.7; extra == "frozen"
Requires-Dist: PeakUtils==1.3.5; extra == "frozen"
Requires-Dist: PyAVM==0.9.8; extra == "frozen"
Requires-Dist: PyJWT==2.11.0; extra == "frozen"
Requires-Dist: PyYAML==6.0.3; extra == "frozen"
Requires-Dist: PyYAML-ft==8.0.0; extra == "frozen"
Requires-Dist: Pygments==2.19.2; extra == "frozen"
Requires-Dist: SQLAlchemy==2.0.46; extra == "frozen"
Requires-Dist: SQLAlchemy-JSONField==1.0.2; extra == "frozen"
Requires-Dist: SQLAlchemy-Utils==0.42.1; extra == "frozen"
Requires-Dist: a2wsgi==1.10.10; extra == "frozen"
Requires-Dist: aioftp==0.27.2; extra == "frozen"
Requires-Dist: aiohappyeyeballs==2.6.1; extra == "frozen"
Requires-Dist: aiohttp==3.13.3; extra == "frozen"
Requires-Dist: aiosignal==1.4.0; extra == "frozen"
Requires-Dist: aiosmtplib==5.1.0; extra == "frozen"
Requires-Dist: aiosqlite==0.21.0; extra == "frozen"
Requires-Dist: alembic==1.18.3; extra == "frozen"
Requires-Dist: amqp==5.3.1; extra == "frozen"
Requires-Dist: annotated-types==0.7.0; extra == "frozen"
Requires-Dist: anyio==4.12.1; extra == "frozen"
Requires-Dist: apache-airflow==3.1.6; extra == "frozen"
Requires-Dist: apache-airflow-core==3.1.6; extra == "frozen"
Requires-Dist: apache-airflow-providers-celery==3.15.1; extra == "frozen"
Requires-Dist: apache-airflow-providers-common-compat==1.12.0; extra == "frozen"
Requires-Dist: apache-airflow-providers-common-io==1.7.1; extra == "frozen"
Requires-Dist: apache-airflow-providers-common-sql==1.30.3; extra == "frozen"
Requires-Dist: apache-airflow-providers-postgres==6.5.2; extra == "frozen"
Requires-Dist: apache-airflow-providers-smtp==2.4.2; extra == "frozen"
Requires-Dist: apache-airflow-providers-standard==1.10.3; extra == "frozen"
Requires-Dist: apache-airflow-task-sdk==1.1.6; extra == "frozen"
Requires-Dist: argcomplete==3.6.3; extra == "frozen"
Requires-Dist: asdf==3.5.0; extra == "frozen"
Requires-Dist: asdf_standard==1.4.0; extra == "frozen"
Requires-Dist: asdf_transform_schemas==0.6.0; extra == "frozen"
Requires-Dist: asgiref==3.11.0; extra == "frozen"
Requires-Dist: asteval==1.0.8; extra == "frozen"
Requires-Dist: astropy==7.0.2; extra == "frozen"
Requires-Dist: astropy-iers-data==0.2026.1.26.0.43.56; extra == "frozen"
Requires-Dist: astropy_healpix==1.1.3; extra == "frozen"
Requires-Dist: asyncpg==0.31.0; extra == "frozen"
Requires-Dist: attrs==25.4.0; extra == "frozen"
Requires-Dist: babel==2.17.0; extra == "frozen"
Requires-Dist: billiard==4.2.4; extra == "frozen"
Requires-Dist: boto3==1.42.38; extra == "frozen"
Requires-Dist: botocore==1.42.38; extra == "frozen"
Requires-Dist: cadwyn==5.4.6; extra == "frozen"
Requires-Dist: celery==5.6.2; extra == "frozen"
Requires-Dist: certifi==2026.1.4; extra == "frozen"
Requires-Dist: cffi==2.0.0; extra == "frozen"
Requires-Dist: charset-normalizer==3.4.4; extra == "frozen"
Requires-Dist: click==8.3.1; extra == "frozen"
Requires-Dist: click-didyoumean==0.3.1; extra == "frozen"
Requires-Dist: click-plugins==1.1.1.2; extra == "frozen"
Requires-Dist: click-repl==0.3.0; extra == "frozen"
Requires-Dist: cloudpickle==3.1.2; extra == "frozen"
Requires-Dist: colorlog==6.10.1; extra == "frozen"
Requires-Dist: contourpy==1.3.3; extra == "frozen"
Requires-Dist: cron_descriptor==2.0.6; extra == "frozen"
Requires-Dist: croniter==6.0.0; extra == "frozen"
Requires-Dist: cryptography==46.0.4; extra == "frozen"
Requires-Dist: cycler==0.12.1; extra == "frozen"
Requires-Dist: dacite==1.9.2; extra == "frozen"
Requires-Dist: dask==2026.1.1; extra == "frozen"
Requires-Dist: dask-image==2025.11.0; extra == "frozen"
Requires-Dist: decorator==5.2.1; extra == "frozen"
Requires-Dist: dill==0.4.1; extra == "frozen"
Requires-Dist: dkist-header-validator==5.3.0; extra == "frozen"
Requires-Dist: dkist-processing-common==12.2.0; extra == "frozen"
Requires-Dist: dkist-processing-core==7.0.1; extra == "frozen"
Requires-Dist: dkist-processing-dlnirsp==0.34.2; extra == "frozen"
Requires-Dist: dkist-processing-math==2.2.1; extra == "frozen"
Requires-Dist: dkist-processing-pac==3.1.1; extra == "frozen"
Requires-Dist: dkist-service-configuration==4.2.0; extra == "frozen"
Requires-Dist: dkist-spectral-lines==3.0.0; extra == "frozen"
Requires-Dist: dkist_fits_specifications==4.20.0; extra == "frozen"
Requires-Dist: dnspython==2.8.0; extra == "frozen"
Requires-Dist: donfig==0.8.1.post1; extra == "frozen"
Requires-Dist: email-validator==2.3.0; extra == "frozen"
Requires-Dist: fastapi==0.117.1; extra == "frozen"
Requires-Dist: fastapi-cli==0.0.20; extra == "frozen"
Requires-Dist: fastjsonschema==2.21.2; extra == "frozen"
Requires-Dist: flower==2.0.1; extra == "frozen"
Requires-Dist: fonttools==4.61.1; extra == "frozen"
Requires-Dist: frozenlist==1.8.0; extra == "frozen"
Requires-Dist: fsspec==2026.1.0; extra == "frozen"
Requires-Dist: globus-sdk==4.3.1; extra == "frozen"
Requires-Dist: google-crc32c==1.8.0; extra == "frozen"
Requires-Dist: googleapis-common-protos==1.72.0; extra == "frozen"
Requires-Dist: gqlclient==1.2.3; extra == "frozen"
Requires-Dist: greenback==1.3.0; extra == "frozen"
Requires-Dist: greenlet==3.3.1; extra == "frozen"
Requires-Dist: grpcio==1.76.0; extra == "frozen"
Requires-Dist: h11==0.16.0; extra == "frozen"
Requires-Dist: httpcore==1.0.9; extra == "frozen"
Requires-Dist: httptools==0.7.1; extra == "frozen"
Requires-Dist: httpx==0.28.1; extra == "frozen"
Requires-Dist: humanize==4.15.0; extra == "frozen"
Requires-Dist: idna==3.11; extra == "frozen"
Requires-Dist: imageio-ffmpeg==0.6.0; extra == "frozen"
Requires-Dist: importlib_metadata==8.7.1; extra == "frozen"
Requires-Dist: itsdangerous==2.2.0; extra == "frozen"
Requires-Dist: jmespath==1.1.0; extra == "frozen"
Requires-Dist: jsonschema==4.26.0; extra == "frozen"
Requires-Dist: jsonschema-specifications==2025.9.1; extra == "frozen"
Requires-Dist: jupyter_core==5.9.1; extra == "frozen"
Requires-Dist: kiwisolver==1.4.9; extra == "frozen"
Requires-Dist: kombu==5.6.2; extra == "frozen"
Requires-Dist: lazy-object-proxy==1.12.0; extra == "frozen"
Requires-Dist: lazy_loader==0.4; extra == "frozen"
Requires-Dist: libcst==1.8.6; extra == "frozen"
Requires-Dist: linkify-it-py==2.0.3; extra == "frozen"
Requires-Dist: llvmlite==0.44.0; extra == "frozen"
Requires-Dist: lmfit==1.3.4; extra == "frozen"
Requires-Dist: locket==1.0.0; extra == "frozen"
Requires-Dist: lockfile==0.12.2; extra == "frozen"
Requires-Dist: loguru==0.7.3; extra == "frozen"
Requires-Dist: markdown-it-py==4.0.0; extra == "frozen"
Requires-Dist: matplotlib==3.10.8; extra == "frozen"
Requires-Dist: mdurl==0.1.2; extra == "frozen"
Requires-Dist: methodtools==0.4.7; extra == "frozen"
Requires-Dist: more-itertools==10.8.0; extra == "frozen"
Requires-Dist: moviepy==2.2.1; extra == "frozen"
Requires-Dist: msgspec==0.20.0; extra == "frozen"
Requires-Dist: multidict==6.7.1; extra == "frozen"
Requires-Dist: natsort==8.4.0; extra == "frozen"
Requires-Dist: nbformat==5.10.4; extra == "frozen"
Requires-Dist: networkx==3.6.1; extra == "frozen"
Requires-Dist: numba==0.61.2; extra == "frozen"
Requires-Dist: numcodecs==0.16.5; extra == "frozen"
Requires-Dist: numpy==2.2.5; extra == "frozen"
Requires-Dist: object-clerk==1.0.0; extra == "frozen"
Requires-Dist: opentelemetry-api==1.39.1; extra == "frozen"
Requires-Dist: opentelemetry-exporter-otlp==1.39.1; extra == "frozen"
Requires-Dist: opentelemetry-exporter-otlp-proto-common==1.39.1; extra == "frozen"
Requires-Dist: opentelemetry-exporter-otlp-proto-grpc==1.39.1; extra == "frozen"
Requires-Dist: opentelemetry-exporter-otlp-proto-http==1.39.1; extra == "frozen"
Requires-Dist: opentelemetry-instrumentation==0.60b1; extra == "frozen"
Requires-Dist: opentelemetry-instrumentation-aiohttp-client==0.60b1; extra == "frozen"
Requires-Dist: opentelemetry-instrumentation-asgi==0.60b1; extra == "frozen"
Requires-Dist: opentelemetry-instrumentation-botocore==0.60b1; extra == "frozen"
Requires-Dist: opentelemetry-instrumentation-celery==0.60b1; extra == "frozen"
Requires-Dist: opentelemetry-instrumentation-dbapi==0.60b1; extra == "frozen"
Requires-Dist: opentelemetry-instrumentation-fastapi==0.60b1; extra == "frozen"
Requires-Dist: opentelemetry-instrumentation-pika==0.60b1; extra == "frozen"
Requires-Dist: opentelemetry-instrumentation-psycopg2==0.60b1; extra == "frozen"
Requires-Dist: opentelemetry-instrumentation-pymongo==0.60b1; extra == "frozen"
Requires-Dist: opentelemetry-instrumentation-redis==0.60b1; extra == "frozen"
Requires-Dist: opentelemetry-instrumentation-requests==0.60b1; extra == "frozen"
Requires-Dist: opentelemetry-instrumentation-sqlalchemy==0.60b1; extra == "frozen"
Requires-Dist: opentelemetry-instrumentation-system-metrics==0.60b1; extra == "frozen"
Requires-Dist: opentelemetry-propagator-aws-xray==1.0.2; extra == "frozen"
Requires-Dist: opentelemetry-proto==1.39.1; extra == "frozen"
Requires-Dist: opentelemetry-sdk==1.39.1; extra == "frozen"
Requires-Dist: opentelemetry-semantic-conventions==0.60b1; extra == "frozen"
Requires-Dist: opentelemetry-util-http==0.60b1; extra == "frozen"
Requires-Dist: outcome==1.3.0.post0; extra == "frozen"
Requires-Dist: packaging==26.0; extra == "frozen"
Requires-Dist: pandas==3.0.0; extra == "frozen"
Requires-Dist: parfive==2.3.1; extra == "frozen"
Requires-Dist: partd==1.4.2; extra == "frozen"
Requires-Dist: pathspec==1.0.4; extra == "frozen"
Requires-Dist: pendulum==3.2.0; extra == "frozen"
Requires-Dist: pika==1.3.2; extra == "frozen"
Requires-Dist: pillow==11.3.0; extra == "frozen"
Requires-Dist: pip==25.3; extra == "frozen"
Requires-Dist: platformdirs==4.5.1; extra == "frozen"
Requires-Dist: pluggy==1.6.0; extra == "frozen"
Requires-Dist: pooch==1.9.0; extra == "frozen"
Requires-Dist: proglog==0.1.12; extra == "frozen"
Requires-Dist: prometheus_client==0.24.1; extra == "frozen"
Requires-Dist: prompt_toolkit==3.0.52; extra == "frozen"
Requires-Dist: propcache==0.4.1; extra == "frozen"
Requires-Dist: protobuf==6.33.5; extra == "frozen"
Requires-Dist: psutil==7.2.2; extra == "frozen"
Requires-Dist: psycopg2-binary==2.9.11; extra == "frozen"
Requires-Dist: pyarrow==23.0.0; extra == "frozen"
Requires-Dist: pycparser==3.0; extra == "frozen"
Requires-Dist: pydantic==2.12.5; extra == "frozen"
Requires-Dist: pydantic-settings==2.12.0; extra == "frozen"
Requires-Dist: pydantic_core==2.41.5; extra == "frozen"
Requires-Dist: pyerfa==2.0.1.5; extra == "frozen"
Requires-Dist: pygtrie==2.5.0; extra == "frozen"
Requires-Dist: pyparsing==3.3.2; extra == "frozen"
Requires-Dist: python-daemon==3.1.2; extra == "frozen"
Requires-Dist: python-dateutil==2.9.0.post0; extra == "frozen"
Requires-Dist: python-dotenv==1.2.1; extra == "frozen"
Requires-Dist: python-multipart==0.0.22; extra == "frozen"
Requires-Dist: python-slugify==8.0.4; extra == "frozen"
Requires-Dist: pytz==2025.2; extra == "frozen"
Requires-Dist: redis==6.4.0; extra == "frozen"
Requires-Dist: referencing==0.37.0; extra == "frozen"
Requires-Dist: reproject==0.19.0; extra == "frozen"
Requires-Dist: requests==2.32.5; extra == "frozen"
Requires-Dist: rich==14.3.1; extra == "frozen"
Requires-Dist: rich-argparse==1.7.2; extra == "frozen"
Requires-Dist: rich-toolkit==0.17.2; extra == "frozen"
Requires-Dist: rpds-py==0.30.0; extra == "frozen"
Requires-Dist: s3transfer==0.16.0; extra == "frozen"
Requires-Dist: scikit-image==0.26.0; extra == "frozen"
Requires-Dist: scipy==1.15.3; extra == "frozen"
Requires-Dist: semantic-version==2.10.0; extra == "frozen"
Requires-Dist: setproctitle==1.3.7; extra == "frozen"
Requires-Dist: shellingham==1.5.4; extra == "frozen"
Requires-Dist: six==1.17.0; extra == "frozen"
Requires-Dist: slicerator==1.1.0; extra == "frozen"
Requires-Dist: sniffio==1.3.1; extra == "frozen"
Requires-Dist: solar-wavelength-calibration==2.0.0; extra == "frozen"
Requires-Dist: sqids==0.5.1; extra == "frozen"
Requires-Dist: sqlparse==0.5.5; extra == "frozen"
Requires-Dist: starlette==0.48.0; extra == "frozen"
Requires-Dist: structlog==25.5.0; extra == "frozen"
Requires-Dist: sunpy==6.1.1; extra == "frozen"
Requires-Dist: svcs==25.1.0; extra == "frozen"
Requires-Dist: tabulate==0.9.0; extra == "frozen"
Requires-Dist: talus==1.3.4; extra == "frozen"
Requires-Dist: tenacity==8.5.0; extra == "frozen"
Requires-Dist: termcolor==3.3.0; extra == "frozen"
Requires-Dist: text-unidecode==1.3; extra == "frozen"
Requires-Dist: tifffile==2026.1.28; extra == "frozen"
Requires-Dist: toolz==1.1.0; extra == "frozen"
Requires-Dist: tornado==6.5.4; extra == "frozen"
Requires-Dist: tqdm==4.67.1; extra == "frozen"
Requires-Dist: traitlets==5.14.3; extra == "frozen"
Requires-Dist: typer==0.21.1; extra == "frozen"
Requires-Dist: typing-inspection==0.4.2; extra == "frozen"
Requires-Dist: typing_extensions==4.15.0; extra == "frozen"
Requires-Dist: tzdata==2025.3; extra == "frozen"
Requires-Dist: tzlocal==5.3.1; extra == "frozen"
Requires-Dist: uc-micro-py==1.0.3; extra == "frozen"
Requires-Dist: uncertainties==3.2.3; extra == "frozen"
Requires-Dist: universal_pathlib==0.2.6; extra == "frozen"
Requires-Dist: urllib3==2.6.3; extra == "frozen"
Requires-Dist: uuid6==2025.0.1; extra == "frozen"
Requires-Dist: uvicorn==0.40.0; extra == "frozen"
Requires-Dist: uvloop==0.22.1; extra == "frozen"
Requires-Dist: vine==5.1.0; extra == "frozen"
Requires-Dist: voluptuous==0.16.0; extra == "frozen"
Requires-Dist: watchfiles==1.1.1; extra == "frozen"
Requires-Dist: wcwidth==0.5.2; extra == "frozen"
Requires-Dist: websockets==16.0; extra == "frozen"
Requires-Dist: wirerope==1.0.0; extra == "frozen"
Requires-Dist: wrapt==1.17.3; extra == "frozen"
Requires-Dist: yamale==6.1.0; extra == "frozen"
Requires-Dist: yarl==1.22.0; extra == "frozen"
Requires-Dist: zarr==3.1.5; extra == "frozen"
Requires-Dist: zipp==3.23.0; extra == "frozen"
